inksplash/__init__.py
inksplash/chameleon.py
inksplash/tests/test_hello.py
inksplash-1.0.4.dist-info/LICENSE
inksplash-1.0.4.dist-info/METADATA
inksplash-1.0.4.dist-info/WHEEL
inksplash-1.0.4.dist-info/top_level.txt
inksplash-1.0.4.dist-info/RECORD
