Metadata-Version: 2.1
Name: inksplash
Version: 1.0.4
Summary: This is a Python package that provides a versatile set of utilities for colorizing and styling text output in terminal environments.
Author-email: Crispen Gari <crispengari@gmail.com>
License: MIT License
Project-URL: homepage, https://github.com/CrispenGari/inksplash
Project-URL: repository, https://github.com/CrispenGari/inksplash
Project-URL: documentation, https://github.com/CrispenGari/inksplash/blob/main/README.md
Project-URL: changelog, https://github.com/CrispenGari/inksplash/blob/main/CHANGELOG.md
Project-URL: issues, https://github.com/CrispenGari/inksplash/issues
Keywords: inksplash,colors,chameleon,console,styling,text-formatting,CLI,ANSI,print,text-decoration
Classifier: Development Status :: 6 - Mature
Classifier: Intended Audience :: Developers
Classifier: License :: OSI Approved :: MIT License
Classifier: Programming Language :: Python :: 3.9
Classifier: Topic :: Software Development :: Libraries :: Python Modules
Classifier: Topic :: Terminals
Classifier: Topic :: Utilities
Classifier: Programming Language :: Python
Classifier: Programming Language :: Python :: 3.12
Classifier: Programming Language :: Python :: 3.11
Classifier: Programming Language :: Python :: 3.10
Classifier: Operating System :: Unix
Classifier: Operating System :: MacOS :: MacOS X
Classifier: Operating System :: Microsoft :: Windows
Classifier: Natural Language :: English
Requires-Python: >=3.9
License-File: LICENSE
